{"idCAM":["3b0ff527-5b33-4b85-8251-bb4e41a3ce72"],"creator":["62c4590804317dc197ecbe8a"],"projectCAM":["SAI_CAMS"],"defocusCAM":[185.5,4713.1,11285.6],"date":[1667295974293],"nodes":[{"id":"f99722c5-a3e4-432e-96b7-c471e30d93cb","value":1,"text":"acceptability of SAI","comment":"Could be a good thing to reduce temperatures","position":{"x":650,"y":400},"isActive":true,"date":1667295975038,"kind":"Node","isSelected":false,"isConnectorSelected":false,"isDraggable":0,"isDeletable":0,"hasElementMoved":false,"eventLog":[{"time":"1667295975038","type":"create node","value":[0]},{"time":"1667296044898","type":"selected","value":[true]},{"time":"1667296045342","type":"selected","value":[false]},{"time":"1667296061041","type":"selected","value":[true]},{"time":"1667296094225","type":"value","value":[1]},{"time":"1667296094225","type":"comment","value":["Could be a good thing to reduce temperatures"]},{"time":"1667296094225","type":"selected","value":[false]},{"time":"1667296096981","type":"selected","value":[true]},{"time":"1667296098843","type":"selected","value":[false]},{"time":"2022-11-01T09:53:24.908Z","type":"position","value":{"x":[644],"y":[395]}},{"time":"1667297095387","type":"selected","value":[true]},{"time":"1667297101051","type":"selected","value":[false]}],"isTextChangeable":0},{"id":"a08659c3-da3d-40aa-b2b0-78336b5442d7","value":-1,"text":"trust in policitical institutions","comment":"Could lead to differences of opinions across the world with political leaders and not everyone going in the same direction.","position":{"x":817,"y":527},"isActive":true,"date":1667295975038,"kind":"Node","isSelected":false,"isConnectorSelected":false,"isDraggable":1,"isDeletable":1,"hasElementMoved":false,"eventLog":[{"time":"1667295975038","type":"create node","value":[0]},{"time":"2022-11-01T10:10:09.396Z","type":"position","value":{"x":[88],"y":[50]}},{"time":"2022-11-01T10:10:09.513Z","type":"position","value":{"x":[263],"y":[173]}},{"time":"2022-11-01T10:10:09.546Z","type":"position","value":{"x":[323],"y":[220]}},{"time":"2022-11-01T10:10:09.597Z","type":"position","value":{"x":[460],"y":[324]}},{"time":"2022-11-01T10:10:09.629Z","type":"position","value":{"x":[565],"y":[401]}},{"time":"2022-11-01T10:10:09.645Z","type":"position","value":{"x":[612],"y":[434]}},{"time":"2022-11-01T10:10:09.714Z","type":"position","value":{"x":[766],"y":[532]}},{"time":"2022-11-01T10:10:09.747Z","type":"position","value":{"x":[827],"y":[555]}},{"time":"2022-11-01T10:10:18.936Z","type":"position","value":{"x":[808],"y":[516]}},{"time":"1667297423918","type":"selected","value":[true]},{"time":"1667297521439","type":"value","value":[-1]},{"time":"1667297521439","type":"comment","value":["Could lead to differences of opinions across the world with political leaders and not everyone going in the same direction."]},{"time":"1667297521439","type":"selected","value":[false]},{"time":"1667297748389","type":"selected","value":[true]},{"time":"1667297779272","type":"selected","value":[false]},{"time":"1667297902086","type":"selected","value":[true]},{"time":"1667297911047","type":"selected","value":[false]}],"isTextChangeable":0},{"id":"91ef98b2-c3a3-40bd-98d7-d6f1b581d256","value":1,"text":"perceived benefits","comment":"Acceptability of SAI could have benefits for the planet as it reduced uts temperature ","position":{"x":666,"y":242},"isActive":true,"date":1667295975038,"kind":"Node","isSelected":false,"isConnectorSelected":false,"isDraggable":1,"isDeletable":1,"hasElementMoved":false,"eventLog":[{"time":"1667295975038","type":"create node","value":[0]},{"time":"2022-11-01T09:53:10.670Z","type":"position","value":{"x":[174],"y":[52]}},{"time":"2022-11-01T09:53:11.132Z","type":"position","value":{"x":[334],"y":[149]}},{"time":"2022-11-01T09:53:11.201Z","type":"position","value":{"x":[450],"y":[205]}},{"time":"2022-11-01T09:53:11.251Z","type":"position","value":{"x":[489],"y":[221]}},{"time":"2022-11-01T09:53:16.723Z","type":"position","value":{"x":[639],"y":[236]}},{"time":"1667296449779","type":"selected","value":[true]},{"time":"1667296527299","type":"value","value":[1]},{"time":"1667296527299","type":"comment","value":["Acceptability of SAI could have benefits for the planet as it reduced uts temperature "]},{"time":"1667296527299","type":"selected","value":[false]},{"time":"1667297085351","type":"selected","value":[true]},{"time":"1667297088597","type":"selected","value":[false]},{"time":"1667297526149","type":"selected","value":[true]},{"time":"1667297532491","type":"selected","value":[false]},{"time":"1667298445609","type":"selected","value":[true]},{"time":"1667298453635","type":"selected","value":[false]},{"time":"2022-11-01T10:28:03.359Z","type":"position","value":{"x":[618],"y":[233]}}],"isTextChangeable":0},{"id":"3d6e75f8-cc44-4598-b95b-3f23c9236f2f","value":10,"text":"perceived risks","comment":"There are risks but this is a technology that could be better than doing nothing.","position":{"x":440,"y":366},"isActive":true,"date":1667295975038,"kind":"Node","isSelected":false,"isConnectorSelected":false,"isDraggable":1,"isDeletable":1,"hasElementMoved":false,"eventLog":[{"time":"1667295975038","type":"create node","value":[0]},{"time":"2022-11-01T10:02:59.094Z","type":"position","value":{"x":[274],"y":[49]}},{"time":"2022-11-01T10:02:59.444Z","type":"position","value":{"x":[345],"y":[211]}},{"time":"2022-11-01T10:02:59.796Z","type":"position","value":{"x":[410],"y":[361]}},{"time":"2022-11-01T10:02:59.879Z","type":"position","value":{"x":[428],"y":[372]}},{"time":"1667296985859","type":"selected","value":[true]},{"time":"1667297052119","type":"value","value":[10]},{"time":"1667297052119","type":"comment","value":["There are risks but this is a technology that could be better than doing nothing."]},{"time":"1667297052119","type":"selected","value":[false]},{"time":"1667297129382","type":"selected","value":[true]},{"time":"1667297140197","type":"selected","value":[false]},{"time":"1667299019131","type":"selected","value":[true]},{"time":"1667299023305","type":"selected","value":[false]}],"isTextChangeable":0},{"id":"d9e2d057-f353-44f8-b7f6-3ff1122cc193","value":-2,"text":"negative feelings","comment":"This could lead to different mindset of the individual and people may become relaxed about climate change and think this is the final solution.","position":{"x":467,"y":561},"isActive":true,"date":1667295975038,"kind":"Node","isSelected":false,"isConnectorSelected":false,"isDraggable":1,"isDeletable":1,"hasElementMoved":false,"eventLog":[{"time":"1667295975038","type":"create node","value":[0]},{"time":"2022-11-01T09:55:32.933Z","type":"position","value":{"x":[373],"y":[45]}},{"time":"2022-11-01T09:55:33.183Z","type":"position","value":{"x":[422],"y":[205]}},{"time":"2022-11-01T09:55:33.434Z","type":"position","value":{"x":[482],"y":[359]}},{"time":"2022-11-01T09:55:33.634Z","type":"position","value":{"x":[524],"y":[422]}},{"time":"2022-11-01T09:55:35.518Z","type":"position","value":{"x":[591],"y":[510]}},{"time":"2022-11-01T09:56:55.560Z","type":"position","value":{"x":[460],"y":[528]}},{"time":"1667296633795","type":"selected","value":[true]},{"time":"1667296712427","type":"value","value":[-2]},{"time":"1667296712427","type":"comment","value":["This could lead to different mindset of the individual and people may become relaxed about climate change and think this is the final solution."]},{"time":"1667296712427","type":"selected","value":[false]}],"isTextChangeable":0},{"id":"01c0f369-c3a6-46cf-9528-2ad3cec94232","value":2,"text":"positive feelings","comment":"If the world works together this could be a good introduction to reduce temperatures.","position":{"x":802,"y":269},"isActive":true,"date":1667295975038,"kind":"Node","isSelected":false,"isConnectorSelected":false,"isDraggable":1,"isDeletable":1,"hasElementMoved":false,"eventLog":[{"time":"1667295975038","type":"create node","value":[0]},{"time":"2022-11-01T09:48:47.218Z","type":"position","value":{"x":[482],"y":[45]}},{"time":"2022-11-01T09:48:47.618Z","type":"position","value":{"x":[610],"y":[202]}},{"time":"2022-11-01T09:48:47.652Z","type":"position","value":{"x":[634],"y":[233]}},{"time":"2022-11-01T09:48:48.485Z","type":"position","value":{"x":[784],"y":[260]}},{"time":"1667296134534","type":"selected","value":[true]},{"time":"1667296160333","type":"value","value":[2]},{"time":"1667296160333","type":"selected","value":[false]},{"time":"1667296188111","type":"selected","value":[true]},{"time":"1667296245491","type":"comment","value":["If the world works together this could be a good introduction to reduce temperatures."]},{"time":"1667296245491","type":"selected","value":[false]},{"time":"2022-11-01T09:52:44.398Z","type":"position","value":{"x":[790],"y":[276]}},{"time":"1667297117978","type":"selected","value":[true]},{"time":"1667297124475","type":"selected","value":[false]},{"time":"1667298880028","type":"selected","value":[true]},{"time":"1667298905466","type":"selected","value":[false]},{"time":"1667299286585","type":"selected","value":[true]},{"time":"1667299296695","type":"selected","value":[false]}],"isTextChangeable":0},{"id":"7cfd076a-2727-4663-a275-dbed97e0fcba","value":3,"text":"Longer lasting Planet","comment":"Planet lasting longer so future generations can enjoy the world as previous generations have before them.","position":{"x":933,"y":151},"isActive":true,"date":1667296108545,"kind":"Node","isSelected":false,"isConnectorSelected":false,"isDraggable":1,"isDeletable":1,"hasElementMoved":false,"eventLog":[{"time":"1667296108546","type":"create node","value":[0]},{"time":"1667296108635","type":"selected","value":[true]},{"time":"1667296121134","type":"selected","value":[false]},{"time":"2022-11-01T09:48:42.500Z","type":"position","value":{"x":[737],"y":[317]}},{"time":"2022-11-01T09:48:44.352Z","type":"position","value":{"x":[599],"y":[156]}},{"time":"2022-11-01T09:48:44.369Z","type":"position","value":{"x":[576],"y":[136]}},{"time":"2022-11-01T09:50:53.455Z","type":"position","value":{"x":[571],"y":[47]}},{"time":"2022-11-01T09:50:53.706Z","type":"position","value":{"x":[722],"y":[97]}},{"time":"2022-11-01T09:50:53.955Z","type":"position","value":{"x":[872],"y":[146]}},{"time":"2022-11-01T09:50:54.223Z","type":"position","value":{"x":[864],"y":[201]}},{"time":"1667296256404","type":"selected","value":[true]},{"time":"1667296347642","type":"text","value":["Longer lasting Planet"]},{"time":"1667296347642","type":"value","value":[3]},{"time":"1667296347642","type":"comment","value":["Planet lasting longer so future generations can enjoy the world as previous generations have before them."]},{"time":"1667296347642","type":"selected","value":[false]},{"time":"2022-11-01T09:52:28.823Z","type":"position","value":{"x":[860],"y":[186]}},{"time":"2022-11-01T09:52:41.077Z","type":"position","value":{"x":[901],"y":[178]}}],"isTextChangeable":1},{"id":"1923947f-49df-4471-833f-753cb6943072","value":-3,"text":"Dangerous Game","comment":"Not knowing the complete side effects of how the technology will effect people and the planet apart from reducing temperatures.","position":{"x":300,"y":639},"isActive":true,"date":1667296746002,"kind":"Node","isSelected":false,"isConnectorSelected":false,"isDraggable":1,"isDeletable":1,"hasElementMoved":false,"eventLog":[{"time":"1667296746002","type":"create node","value":[0]},{"time":"1667296746097","type":"selected","value":[true]},{"time":"1667296748004","type":"selected","value":[false]},{"time":"2022-11-01T09:59:08.622Z","type":"position","value":{"x":[374],"y":[603]}},{"time":"1667296757852","type":"selected","value":[true]},{"time":"1667296822846","type":"text","value":["Dangerous Game"]},{"time":"1667296822846","type":"selected","value":[false]},{"time":"1667296823799","type":"selected","value":[true]},{"time":"1667296885214","type":"value","value":[-3]},{"time":"1667296885214","type":"comment","value":["Not knowing the complete side effects of how the technology will effect people and the planet apart from reducing temperatures."]},{"time":"1667296885214","type":"selected","value":[false]}],"isTextChangeable":1},{"id":"783fbce8-a90b-4eb5-a471-181ad513b204","value":1,"text":"Great Future","comment":"Possibility of a greater future for everyone.","position":{"x":1049,"y":295},"isActive":true,"date":1667296926343,"kind":"Node","isSelected":false,"isConnectorSelected":false,"isDraggable":1,"isDeletable":1,"hasElementMoved":false,"eventLog":[{"time":"1667296926343","type":"create node","value":[0]},{"time":"2022-11-01T10:02:07.616Z","type":"position","value":{"x":[1063],"y":[210]}},{"time":"1667296934909","type":"selected","value":[true]},{"time":"1667296968392","type":"text","value":["Great Future"]},{"time":"1667296968392","type":"value","value":[1]},{"time":"1667296968392","type":"comment","value":["Possibility of a greater future for everyone."]},{"time":"1667296968392","type":"selected","value":[false]},{"time":"1667299330483","type":"selected","value":[true]},{"time":"1667299334608","type":"selected","value":[false]}],"isTextChangeable":1},{"id":"a714f05d-9f26-4dc9-a297-24cc2b9313d1","value":-1,"text":"Climate change","comment":"People still need to concentrate and improve everything they do to reduce climate change. The introduction of SAI could be risky to what the world has already started with people thinking this is the solution.","position":{"x":263,"y":337},"isActive":true,"date":1667297140379,"kind":"Node","isSelected":false,"isConnectorSelected":false,"isDraggable":1,"isDeletable":1,"hasElementMoved":false,"eventLog":[{"time":"1667297140379","type":"create node","value":[0]},{"time":"2022-11-01T10:05:44.214Z","type":"position","value":{"x":[298],"y":[327]}},{"time":"1667297147521","type":"selected","value":[true]},{"time":"1667297185212","type":"text","value":["Climate change"]},{"time":"1667297185212","type":"selected","value":[false]},{"time":"2022-11-01T10:06:25.964Z","type":"position","value":{"x":[284],"y":[336]}},{"time":"1667297188852","type":"selected","value":[true]},{"time":"1667297343381","type":"comment","value":["People still need to concentrate and improve everything they do to reduce climate change. The introduction of SAI could be risky to what the world has already started with people thinking this is the solution."]},{"time":"1667297343381","type":"selected","value":[false]},{"time":"2022-11-01T10:09:05.562Z","type":"position","value":{"x":[275],"y":[336]}},{"time":"1667297348458","type":"selected","value":[true]},{"time":"1667297352633","type":"value","value":[-1]},{"time":"1667297352633","type":"selected","value":[false]},{"time":"1667298916957","type":"selected","value":[true]},{"time":"1667298929707","type":"selected","value":[false]},{"time":"1667299025476","type":"selected","value":[true]},{"time":"1667299029156","type":"selected","value":[false]}],"isTextChangeable":1},{"id":"ce974fb3-9dcb-4ed6-9967-acc8fd429910","value":1,"text":"Low costs","comment":"Lower cost to implement than other technologies so could be a good starting point.","position":{"x":633,"y":124},"isActive":true,"date":1667297533189,"kind":"Node","isSelected":false,"isConnectorSelected":false,"isDraggable":1,"isDeletable":1,"hasElementMoved":false,"eventLog":[{"time":1667297533189,"type":"create node","value":"0"},{"time":1667297533229,"type":"selected","value":"TRUE"},{"time":1667297540293,"type":"value","value":"1"},{"time":1667297540293,"type":"selected","value":"FALSE"},{"time":1667297554303,"type":"selected","value":"TRUE"},{"time":1667297626372,"type":"text","value":"Low costs"},{"time":1667297626372,"type":"comment","value":"Lower cost to implement than other technologies so could be a good starting point."},{"time":1667297626372,"type":"selected","value":"FALSE"},{"time":1667298413549,"type":"selected","value":"TRUE"},{"time":1667298439981,"type":"selected","value":"FALSE"}],"isTextChangeable":1},{"id":"29695546-a4dc-453d-bd4d-a5f0a572c2fa","value":-1,"text":"No guarantee","comment":"No guarantee this technology will be successful and the negatives could outweigh the positives.","position":{"x":260,"y":220},"isActive":true,"date":1667297639324,"kind":"Node","isSelected":false,"isConnectorSelected":false,"isDraggable":1,"isDeletable":1,"hasElementMoved":false,"eventLog":[{"time":1667297639324,"type":"create node","value":"0"},{"time":1667297639421,"type":"selected","value":"TRUE"},{"time":1667297714468,"type":"text","value":"No guarantee"},{"time":1667297714468,"type":"value","value":"-1"},{"time":1667297714468,"type":"comment","value":"No guarantee this technology will be successful and the negatives could outweigh the positives."},{"time":1667297714468,"type":"selected","value":"FALSE"},{"time":1667298931245,"type":"selected","value":"TRUE"},{"time":1667298941994,"type":"selected","value":"FALSE"}],"isTextChangeable":1},{"id":"a561ffcf-ce5d-4bbc-9414-7947e7be2798","value":2,"text":"Pulling together","comment":"All politicians and leaders could pull together and save the planet. Or at least make steps towards this.","position":{"x":999,"y":634},"isActive":true,"date":1667297823351,"kind":"Node","isSelected":false,"isConnectorSelected":false,"isDraggable":1,"isDeletable":1,"hasElementMoved":false,"eventLog":[{"time":"1667297823351","type":"create node","value":[0]},{"time":"1667297828332","type":"selected","value":[true]},{"time":"1667297901246","type":"text","value":["Pulling together"]},{"time":"1667297901246","type":"value","value":[2]},{"time":"1667297901246","type":"comment","value":["All politicians and leaders could pull together and save the planet. Or at least make steps towards this."]},{"time":"1667297901246","type":"selected","value":[false]},{"time":"2022-11-01T10:18:45.600Z","type":"position","value":{"x":[940],"y":[598]}},{"time":"1667298905586","type":"selected","value":[true]},{"time":"1667298911201","type":"selected","value":[false]}],"isTextChangeable":1},{"id":"10a571d7-ae24-457b-bb04-b648ca848654","value":2,"text":"World Leaders","comment":"All need to come together to make this work and get the ball rolling.","position":{"x":654,"y":525},"isActive":true,"date":1667298107709,"kind":"Node","isSelected":false,"isConnectorSelected":false,"isDraggable":1,"isDeletable":1,"hasElementMoved":false,"eventLog":[{"time":"1667298107709","type":"create node","value":[0]},{"time":"1667298107789","type":"selected","value":[true]},{"time":"1667298166548","type":"text","value":["World Leaders"]},{"time":"1667298166548","type":"value","value":[2]},{"time":"1667298166548","type":"comment","value":["All need to come together to make this work and get the ball rolling."]},{"time":"1667298166548","type":"selected","value":[false]},{"time":"2022-11-01T10:22:52.047Z","type":"position","value":{"x":[653],"y":[511]}},{"time":"1667298178128","type":"selected","value":[true]},{"time":"1667298179867","type":"selected","value":[false]}],"isTextChangeable":1},{"id":"e9bc54f6-b4d9-4759-b6ac-b7703d841a34","value":1,"text":"Sub Groups","comment":"Each country needs to create climate groups to introduce this technology to save the planet and relay the positives and negatives across the globe.","position":{"x":658,"y":658},"isActive":true,"date":1667298182366,"kind":"Node","isSelected":false,"isConnectorSelected":false,"isDraggable":1,"isDeletable":1,"hasElementMoved":false,"eventLog":[{"time":"1667298182366","type":"create node","value":[0]},{"time":"1667298182472","type":"selected","value":[true]},{"time":"1667298210764","type":"text","value":["Sub Groups"]},{"time":"1667298210764","type":"selected","value":[false]},{"time":"2022-11-01T10:23:31.258Z","type":"position","value":{"x":[654],"y":[600]}},{"time":"1667298213353","type":"selected","value":[true]},{"time":"1667298353770","type":"comment","value":["Each country needs to create climate groups to introduce this technology to save the planet and relay the positives and negatives across the globe."]},{"time":"1667298353770","type":"selected","value":[false]},{"time":"2022-11-01T10:25:56.553Z","type":"position","value":{"x":[654],"y":[607]}},{"time":"1667299418962","type":"selected","value":[true]},{"time":"1667299429939","type":"selected","value":[false]},{"time":"1667299433543","type":"selected","value":[true]},{"time":"1667299436975","type":"value","value":[1]},{"time":"1667299436975","type":"selected","value":[false]}],"isTextChangeable":1},{"id":"25036eea-3ada-41bb-b6c2-e46b2d6d3194","value":10,"text":"Implemented","comment":"Needs to be implemented rather soon to start to reduce temperatures.","position":{"x":510,"y":211},"isActive":true,"date":1667298456149,"kind":"Node","isSelected":false,"isConnectorSelected":false,"isDraggable":1,"isDeletable":1,"hasElementMoved":false,"eventLog":[{"time":"1667298456150","type":"create node","value":[0]},{"time":"1667298456223","type":"selected","value":[true]},{"time":"1667298480360","type":"text","value":["Implemented"]},{"time":"1667298480360","type":"selected","value":[false]},{"time":"2022-11-01T10:28:02.063Z","type":"position","value":{"x":[512],"y":[216]}},{"time":"2022-11-01T10:28:07.156Z","type":"position","value":{"x":[501],"y":[209]}},{"time":"1667298501054","type":"selected","value":[true]},{"time":"1667298561653","type":"value","value":[10]},{"time":"1667298561653","type":"comment","value":["Needs to be implemented rather soon to start to reduce temperatures."]},{"time":"1667298561653","type":"selected","value":[false]}],"isTextChangeable":1},{"id":"bca69691-71fe-4e81-8aef-7a9cf6e7cd08","value":2,"text":"How","comment":"Releasing sulphur particles in the air using aeroplanes which are 50,000 feet above the earths surface.","position":{"x":386,"y":122},"isActive":true,"date":1667298577139,"kind":"Node","isSelected":false,"isConnectorSelected":false,"isDraggable":1,"isDeletable":1,"hasElementMoved":false,"eventLog":[{"time":"1667298577139","type":"create node","value":[0]},{"time":"1667298577236","type":"selected","value":[true]},{"time":"1667298584528","type":"text","value":["How"]},{"time":"1667298584528","type":"selected","value":[false]},{"time":"2022-11-01T10:29:45.105Z","type":"position","value":{"x":[416],"y":[128]}},{"time":"1667298586582","type":"selected","value":[true]},{"time":"1667298718840","type":"value","value":[2]},{"time":"1667298718840","type":"comment","value":["Releasing sulphur particles in the air using aeroplanes which are 50,000 feet above the earths surface."]},{"time":"1667298718840","type":"selected","value":[false]},{"time":"2022-11-01T10:32:51.325Z","type":"position","value":{"x":[373],"y":[92]}}],"isTextChangeable":1},{"id":"c6a306cc-13cf-4573-95c0-80db03d2d619","value":10,"text":"World Coming together","comment":"Every country and every plane taking its part brings the world together.","position":{"x":196,"y":60},"isActive":true,"date":1667298749112,"kind":"Node","isSelected":false,"isConnectorSelected":false,"isDraggable":1,"isDeletable":1,"hasElementMoved":false,"eventLog":[{"time":"1667298749112","type":"create node","value":[0]},{"time":"1667298749176","type":"selected","value":[true]},{"time":"1667298766921","type":"text","value":["World Coming together"]},{"time":"1667298766921","type":"selected","value":[false]},{"time":"2022-11-01T10:32:54.923Z","type":"position","value":{"x":[259],"y":[50]}},{"time":"1667298779736","type":"selected","value":[true]},{"time":"1667298826392","type":"comment","value":["Every country and every plane taking its part brings the world together."]},{"time":"1667298826392","type":"selected","value":[false]},{"time":"1667298865247","type":"selected","value":[true]},{"time":"1667298873472","type":"value","value":[10]},{"time":"1667298873472","type":"selected","value":[false]},{"time":"1667299621928","type":"selected","value":[true]},{"time":"1667299630472","type":"selected","value":[false]},{"time":"2022-11-01T10:47:23.028Z","type":"position","value":{"x":[217],"y":[59]}}],"isTextChangeable":1},{"id":"870ecccb-2b71-4656-9d05-d047ce30f154","value":-2,"text":"Weather","comment":"Could lead to acid rain","position":{"x":220,"y":479},"isActive":true,"date":1667298942526,"kind":"Node","isSelected":false,"isConnectorSelected":false,"isDraggable":1,"isDeletable":1,"hasElementMoved":false,"eventLog":[{"time":"1667298942526","type":"create node","value":[0]},{"time":"1667298944082","type":"selected","value":[true]},{"time":"1667298968570","type":"text","value":["Weather"]},{"time":"1667298968570","type":"selected","value":[false]},{"time":"1667298971174","type":"selected","value":[true]},{"time":"1667298974105","type":"selected","value":[false]},{"time":"2022-11-01T10:36:18.957Z","type":"position","value":{"x":[221],"y":[420]}},{"time":"1667298981752","type":"selected","value":[true]},{"time":"1667299002415","type":"value","value":[-2]},{"time":"1667299002415","type":"comment","value":["Could lead to acid rain"]},{"time":"1667299002415","type":"selected","value":[false]}],"isTextChangeable":1},{"id":"3fcf905e-d45a-4e08-8439-883c75e7bfbd","value":-1,"text":"Deployed for years","comment":"Needs to be deployed for years without knowing th efull extent of costs ","position":{"x":381,"y":473},"isActive":true,"date":1667299050645,"kind":"Node","isSelected":false,"isConnectorSelected":false,"isDraggable":1,"isDeletable":1,"hasElementMoved":false,"eventLog":[{"time":"1667299050645","type":"create node","value":[0]},{"time":"1667299052258","type":"selected","value":[true]},{"time":"1667299064752","type":"text","value":["Deployed for years"]},{"time":"1667299064752","type":"selected","value":[false]},{"time":"2022-11-01T10:37:45.530Z","type":"position","value":{"x":[414],"y":[447]}},{"time":"1667299069714","type":"selected","value":[true]},{"time":"1667299073805","type":"value","value":[-1]},{"time":"1667299073805","type":"selected","value":[false]},{"time":"1667299075876","type":"selected","value":[true]},{"time":"1667299113636","type":"comment","value":["Needs to be deployed for years without knowing th efull extent of costs "]},{"time":"1667299113636","type":"selected","value":[false]}],"isTextChangeable":1},{"id":"99725676-875c-4739-883c-8b5f4d401f50","value":-2,"text":"Set Goals","comment":"It doesn't Inherent the causes of climate change so we still need to continue working together towards goals already set.","position":{"x":99,"y":329},"isActive":true,"date":1667299146977,"kind":"Node","isSelected":false,"isConnectorSelected":false,"isDraggable":1,"isDeletable":1,"hasElementMoved":false,"eventLog":[{"time":"1667299146977","type":"create node","value":[0]},{"time":"1667299148106","type":"selected","value":[true]},{"time":"1667299228590","type":"text","value":["Set Goals"]},{"time":"1667299228590","type":"comment","value":["It doesn't Inherent the causes of climate change so we still need to continue working together towards goals already set."]},{"time":"1667299228590","type":"selected","value":[false]},{"time":"2022-11-01T10:40:37.090Z","type":"position","value":{"x":[133],"y":[328]}},{"time":"1667299250667","type":"selected","value":[true]},{"time":"1667299255697","type":"value","value":[-2]},{"time":"1667299255697","type":"selected","value":[false]}],"isTextChangeable":1},{"id":"76de18ae-c459-482f-813e-373dcb85a211","value":1,"text":"Lifestyle to continue","comment":"We still need to stay positive and make our own changes and continue with our lifestyle changes along with this new added technology.","position":{"x":889,"y":385},"isActive":true,"date":1667299315315,"kind":"Node","isSelected":false,"isConnectorSelected":false,"isDraggable":1,"isDeletable":1,"hasElementMoved":false,"eventLog":[{"time":"1667299315315","type":"create node","value":[0]},{"time":"2022-11-01T10:42:05.186Z","type":"position","value":{"x":[883],"y":[347]}},{"time":"2022-11-01T10:43:32.843Z","type":"position","value":{"x":[880],"y":[381]}},{"time":"2022-11-01T10:44:34.823Z","type":"position","value":{"x":[884],"y":[422]}},{"time":"1667299479265","type":"selected","value":[true]},{"time":"1667299573003","type":"text","value":["Lifestyle to continue"]},{"time":"1667299573003","type":"comment","value":["We still need to stay positive and make our own changes and continue with our lifestyle changes along with this new added technology."]},{"time":"1667299573003","type":"selected","value":[false]},{"time":"2022-11-01T10:46:14.251Z","type":"position","value":{"x":[872],"y":[377]}},{"time":"1667299577998","type":"selected","value":[true]},{"time":"1667299585240","type":"value","value":[1]},{"time":"1667299585240","type":"selected","value":[false]}],"isTextChangeable":1},{"id":"5c4a85a0-9583-4666-b691-376b9e192b79","value":1,"text":"This could work","comment":"This could work in the long run working together.","position":{"x":79,"y":167},"isActive":true,"date":1667299317532,"kind":"Node","isSelected":false,"isConnectorSelected":false,"isDraggable":1,"isDeletable":1,"hasElementMoved":false,"eventLog":[{"time":"1667299317532","type":"create node","value":[0]},{"time":"2022-11-01T10:46:36.987Z","type":"position","value":{"x":[1066],"y":[440]}},{"time":"2022-11-01T10:46:59.099Z","type":"position","value":{"x":[1062],"y":[476]}},{"time":"2022-11-01T10:46:59.182Z","type":"position","value":{"x":[859],"y":[415]}},{"time":"2022-11-01T10:46:59.216Z","type":"position","value":{"x":[706],"y":[355]}},{"time":"2022-11-01T10:46:59.232Z","type":"position","value":{"x":[637],"y":[322]}},{"time":"2022-11-01T10:46:59.266Z","type":"position","value":{"x":[523],"y":[259]}},{"time":"2022-11-01T10:46:59.315Z","type":"position","value":{"x":[372],"y":[167]}},{"time":"2022-11-01T10:46:59.560Z","type":"position","value":{"x":[217],"y":[85]}},{"time":"1667299631975","type":"selected","value":[true]},{"time":"1667299641424","type":"text","value":["This could work"]},{"time":"1667299641424","type":"selected","value":[false]},{"time":"2022-11-01T10:47:23.378Z","type":"position","value":{"x":[83],"y":[69]}},{"time":"2022-11-01T10:47:24.224Z","type":"position","value":{"x":[85],"y":[71]}},{"time":"2022-11-01T10:47:29.994Z","type":"position","value":{"x":[90],"y":[98]}},{"time":"1667299659517","type":"selected","value":[true]},{"time":"1667299705996","type":"comment","value":["This could work in the long run working together."]},{"time":"1667299705996","type":"selected","value":[false]},{"time":"1667299707938","type":"selected","value":[true]},{"time":"1667299710614","type":"value","value":[1]},{"time":"1667299710614","type":"selected","value":[false]}],"isTextChangeable":1},{"id":"b210bf86-c18c-4d6f-99af-5311e9d25ffe","value":2,"text":"Generations","comment":"Generations could be saved if we bring in this technology working alongside other technologies.","position":{"x":1197,"y":354},"isActive":true,"date":1667299318332,"kind":"Node","isSelected":false,"isConnectorSelected":false,"isDraggable":1,"isDeletable":1,"hasElementMoved":false,"eventLog":[{"time":"1667299318332","type":"create node","value":[0]},{"time":"1667299341086","type":"selected","value":[true]},{"time":"1667299353447","type":"text","value":["Generations"]},{"time":"1667299353447","type":"value","value":[2]},{"time":"1667299353447","type":"selected","value":[false]},{"time":"2022-11-01T10:42:40.664Z","type":"position","value":{"x":[1161],"y":[337]}},{"time":"1667299367738","type":"selected","value":[true]},{"time":"1667299408367","type":"comment","value":["Generations could be saved if we bring in this technology working alongside other technologies."]},{"time":"1667299408367","type":"selected","value":[false]}],"isTextChangeable":1}],"connectors":[{"id":"0d1ce6f2-0bad-4930-81c8-7018ab6023c4","source":"f99722c5-a3e4-432e-96b7-c471e30d93cb","target":"01c0f369-c3a6-46cf-9528-2ad3cec94232","agreement":true,"isActive":true,"date":1667296163331,"kind":"Connector","isSelected":false,"intensity":6,"isDeletable":true,"isOver":false,"isBidirectional":false,"eventLog":[{"time":1667296163331,"type":"create connection"},{"time":1667296170638,"type":"selected","value":1},{"time":1667296185238,"type":"change intensity of connector","value":6},{"time":1667296185238,"type":"selected","value":0}]},{"id":"7d175a6b-7989-43bd-a27a-40114c2e701c","source":"7cfd076a-2727-4663-a275-dbed97e0fcba","target":"01c0f369-c3a6-46cf-9528-2ad3cec94232","agreement":true,"isActive":true,"date":1667296354808,"kind":"Connector","isSelected":false,"intensity":6,"isDeletable":true,"isOver":false,"isBidirectional":false,"eventLog":[{"time":1667296354808,"type":"create connection"},{"time":1667296369493,"type":"selected","value":1},{"time":1667296375951,"type":"change intensity of connector","value":6},{"time":1667296375951,"type":"selected","value":0}]},{"id":"55ea42ab-20d1-4984-a6a9-d1db3be41e8f","source":"91ef98b2-c3a3-40bd-98d7-d6f1b581d256","target":"f99722c5-a3e4-432e-96b7-c471e30d93cb","agreement":true,"isActive":true,"date":1667296406792,"kind":"Connector","isSelected":false,"intensity":6,"isDeletable":true,"isOver":false,"isBidirectional":true,"eventLog":[{"time":1667296406792,"type":"create connection"},{"time":1667296412456,"type":"selected","value":1},{"time":1667296413744,"type":"bidirection","value":1},{"time":1667296447024,"type":"change intensity of connector","value":6},{"time":1667296447024,"type":"selected","value":0}]},{"id":"9ee287ce-d7e5-497e-8369-0bbb35a5fe1a","source":"f99722c5-a3e4-432e-96b7-c471e30d93cb","target":"d9e2d057-f353-44f8-b7f6-3ff1122cc193","agreement":true,"isActive":true,"date":1667296542836,"kind":"Connector","isSelected":false,"intensity":3,"isDeletable":true,"isOver":false,"isBidirectional":false,"eventLog":[{"time":1667296542836,"type":"create connection"},{"time":1667296606163,"type":"selected","value":1},{"time":1667296608457,"type":"bidirection","value":1},{"time":1667296609157,"type":"bidirection","value":1},{"time":1667296609840,"type":"bidirection","value":1},{"time":1667296610391,"type":"direction"},{"time":1667296614295,"type":"change intensity of connector","value":3},{"time":1667296614295,"type":"selected","value":0}]},{"id":"0374f084-5137-4a1c-9a19-4b91a18290de","source":"d9e2d057-f353-44f8-b7f6-3ff1122cc193","target":"1923947f-49df-4471-833f-753cb6943072","agreement":true,"isActive":true,"date":1667296753687,"kind":"Connector","isSelected":false,"intensity":3,"isDeletable":true,"isOver":false,"isBidirectional":true,"eventLog":[{"time":1667296753687,"type":"create connection"},{"time":1667296888842,"type":"selected","value":1},{"time":1667296890064,"type":"bidirection","value":1},{"time":1667296891617,"type":"change intensity of connector","value":3},{"time":1667296891617,"type":"selected","value":0}]},{"id":"1beef60a-154e-418e-ac43-47a3e03f7623","source":"7cfd076a-2727-4663-a275-dbed97e0fcba","target":"783fbce8-a90b-4eb5-a471-181ad513b204","agreement":true,"isActive":true,"date":1667296931845,"kind":"Connector","isSelected":false,"intensity":3,"isDeletable":true,"isOver":false,"isBidirectional":false,"eventLog":[{"time":1667296931845,"type":"create connection"}]},{"id":"cc858401-47ea-4ad9-b13e-81c4732682fe","source":"f99722c5-a3e4-432e-96b7-c471e30d93cb","target":"3d6e75f8-cc44-4598-b95b-3f23c9236f2f","agreement":true,"isActive":true,"date":1667297055135,"kind":"Connector","isSelected":false,"intensity":3,"isDeletable":true,"isOver":false,"isBidirectional":false,"eventLog":[{"time":1667297055135,"type":"create connection"},{"time":1667297060414,"type":"selected","value":1},{"time":1667297068958,"type":"change intensity of connector","value":3},{"time":1667297068958,"type":"selected","value":0}]},{"id":"4abc6d21-06eb-41c5-b941-6d653c8fc14d","source":"3d6e75f8-cc44-4598-b95b-3f23c9236f2f","target":"a714f05d-9f26-4dc9-a297-24cc2b9313d1","agreement":false,"isActive":true,"date":1667297354898,"kind":"Connector","isSelected":false,"intensity":6,"isDeletable":true,"isOver":false,"isBidirectional":false,"eventLog":[{"time":1667297354898,"type":"create connection"},{"time":1667297360956,"type":"selected","value":1},{"time":1667297368888,"type":"change intensity of connector","value":-6},{"time":1667297368888,"type":"selected","value":0}]},{"id":"d875f61e-7050-4453-8d1b-1f8fa53e4105","source":"f99722c5-a3e4-432e-96b7-c471e30d93cb","target":"a08659c3-da3d-40aa-b2b0-78336b5442d7","agreement":true,"isActive":true,"date":1667297415585,"kind":"Connector","isSelected":false,"intensity":3,"isDeletable":true,"isOver":false,"isBidirectional":false,"eventLog":[{"time":1667297415585,"type":"create connection"}]},{"id":"79ca321b-7844-4c54-8e9b-303b5f2bc4f3","source":"91ef98b2-c3a3-40bd-98d7-d6f1b581d256","target":"ce974fb3-9dcb-4ed6-9967-acc8fd429910","agreement":true,"isActive":true,"date":1667297542459,"kind":"Connector","isSelected":false,"intensity":3,"isDeletable":true,"isOver":false,"isBidirectional":false,"eventLog":[{"time":1667297542459,"type":"create connection"},{"time":1667297544532,"type":"selected","value":1},{"time":1667297545710,"type":"bidirection","value":1},{"time":1667297547193,"type":"direction"},{"time":1667297549397,"type":"change intensity of connector","value":3},{"time":1667297549397,"type":"selected","value":0}]},{"id":"f31bbef7-5883-484a-ae31-47e49649b41b","source":"a714f05d-9f26-4dc9-a297-24cc2b9313d1","target":"29695546-a4dc-453d-bd4d-a5f0a572c2fa","agreement":true,"isActive":true,"date":1667297719049,"kind":"Connector","isSelected":false,"intensity":3,"isDeletable":true,"isOver":false,"isBidirectional":false,"eventLog":[{"time":1667297719049,"type":"create connection"},{"time":1667297722847,"type":"selected","value":1},{"time":1667297726351,"type":"bidirection","value":1},{"time":1667297727452,"type":"direction"},{"time":1667297729255,"type":"change intensity of connector","value":3},{"time":1667297729255,"type":"selected","value":0}]},{"id":"93139895-28d7-40b8-9796-1862898ebb38","source":"a561ffcf-ce5d-4bbc-9414-7947e7be2798","target":"a08659c3-da3d-40aa-b2b0-78336b5442d7","agreement":true,"isActive":true,"date":1667297912245,"kind":"Connector","isSelected":false,"intensity":3,"isDeletable":true,"isOver":false,"isBidirectional":true,"eventLog":[{"time":1667297912245,"type":"create connection"},{"time":1667297918110,"type":"selected","value":1},{"time":1667297919864,"type":"bidirection","value":1},{"time":1667297924786,"type":"change intensity of connector","value":3},{"time":1667297924786,"type":"selected","value":0}]},{"id":"53cfe597-6720-462f-ad4b-78d4e93ee0a8","source":"f99722c5-a3e4-432e-96b7-c471e30d93cb","target":"10a571d7-ae24-457b-bb04-b648ca848654","agreement":true,"isActive":true,"date":1667298170779,"kind":"Connector","isSelected":false,"intensity":3,"isDeletable":true,"isOver":false,"isBidirectional":false,"eventLog":[{"time":1667298170779,"type":"create connection"}]},{"id":"8b96b177-dd18-4ddb-a571-3da6ba238346","source":"e9bc54f6-b4d9-4759-b6ac-b7703d841a34","target":"10a571d7-ae24-457b-bb04-b648ca848654","agreement":true,"isActive":true,"date":1667298355483,"kind":"Connector","isSelected":false,"intensity":6,"isDeletable":true,"isOver":false,"isBidirectional":true,"eventLog":[{"time":1667298355483,"type":"create connection"},{"time":1667298359581,"type":"selected","value":1},{"time":1667298362285,"type":"bidirection","value":1},{"time":1667298369857,"type":"change intensity of connector","value":6},{"time":1667298369857,"type":"selected","value":0}]},{"id":"5cb254ea-b0c9-4810-9e04-7336d4b414f4","source":"91ef98b2-c3a3-40bd-98d7-d6f1b581d256","target":"25036eea-3ada-41bb-b6c2-e46b2d6d3194","agreement":true,"isActive":true,"date":1667298488210,"kind":"Connector","isSelected":false,"intensity":3,"isDeletable":true,"isOver":false,"isBidirectional":false,"eventLog":[{"time":1667298488210,"type":"create connection"},{"time":1667298492908,"type":"selected","value":1},{"time":1667298494278,"type":"direction"},{"time":1667298498600,"type":"change intensity of connector","value":3},{"time":1667298498600,"type":"selected","value":0}]},{"id":"4ba71ca2-4765-4898-bd61-15336a711d35","source":"25036eea-3ada-41bb-b6c2-e46b2d6d3194","target":"bca69691-71fe-4e81-8aef-7a9cf6e7cd08","agreement":true,"isActive":true,"date":1667298720153,"kind":"Connector","isSelected":false,"intensity":6,"isDeletable":true,"isOver":false,"isBidirectional":false,"eventLog":[{"time":1667298720153,"type":"create connection"},{"time":1667298721715,"type":"selected","value":1},{"time":1667298724823,"type":"change intensity of connector","value":6},{"time":1667298724823,"type":"selected","value":0}]},{"id":"b451f0cc-f7f9-48b3-be9e-198150da611c","source":"bca69691-71fe-4e81-8aef-7a9cf6e7cd08","target":"c6a306cc-13cf-4573-95c0-80db03d2d619","agreement":true,"isActive":true,"date":1667298776304,"kind":"Connector","isSelected":false,"intensity":3,"isDeletable":true,"isOver":false,"isBidirectional":false,"eventLog":[{"time":1667298776304,"type":"create connection"}]},{"id":"b4de91a1-474c-4a5d-9205-4cb9dbcb9e87","source":"a714f05d-9f26-4dc9-a297-24cc2b9313d1","target":"870ecccb-2b71-4656-9d05-d047ce30f154","agreement":true,"isActive":true,"date":1667298970752,"kind":"Connector","isSelected":false,"intensity":3,"isDeletable":true,"isOver":false,"isBidirectional":true,"eventLog":[{"time":1667298970752,"type":"create connection"},{"time":1667298974191,"type":"selected","value":1},{"time":1667298975803,"type":"bidirection","value":1},{"time":1667298978423,"type":"change intensity of connector","value":3},{"time":1667298978423,"type":"selected","value":0}]},{"id":"cdaed971-224b-4e5a-8ccc-c57b167df2b1","source":"3d6e75f8-cc44-4598-b95b-3f23c9236f2f","target":"3fcf905e-d45a-4e08-8439-883c75e7bfbd","agreement":true,"isActive":true,"date":1667299068100,"kind":"Connector","isSelected":false,"intensity":3,"isDeletable":true,"isOver":false,"isBidirectional":false,"eventLog":[{"time":1667299068100,"type":"create connection"}]},{"id":"a406f3f9-cc35-4054-adf5-16172459d8ac","source":"a714f05d-9f26-4dc9-a297-24cc2b9313d1","target":"99725676-875c-4739-883c-8b5f4d401f50","agreement":false,"isActive":true,"date":1667299230103,"kind":"Connector","isSelected":false,"intensity":3,"isDeletable":true,"isOver":false,"isBidirectional":false,"eventLog":[{"time":1667299230103,"type":"create connection"},{"time":1667299232767,"type":"selected","value":1},{"time":1667299234221,"type":"direction"},{"time":1667299236525,"type":"change intensity of connector","value":3},{"time":1667299236525,"type":"selected","value":0},{"time":1667299238968,"type":"selected","value":1},{"time":1667299240406,"type":"direction"},{"time":1667299248979,"type":"change intensity of connector","value":-3},{"time":1667299248979,"type":"selected","value":0}]},{"id":"23911de7-5899-45e5-8adc-76716603b3e5","source":"783fbce8-a90b-4eb5-a471-181ad513b204","target":"b210bf86-c18c-4d6f-99af-5311e9d25ffe","agreement":true,"isActive":true,"date":1667299359596,"kind":"Connector","isSelected":false,"intensity":3,"isDeletable":true,"isOver":false,"isBidirectional":false,"eventLog":[{"time":1667299359596,"type":"create connection"},{"time":1667299362976,"type":"selected","value":1},{"time":1667299364197,"type":"direction"},{"time":1667299365367,"type":"change intensity of connector","value":3},{"time":1667299365367,"type":"selected","value":0}]},{"id":"03f71ab9-fa71-4b04-9148-521cbe355cc3","source":"01c0f369-c3a6-46cf-9528-2ad3cec94232","target":"76de18ae-c459-482f-813e-373dcb85a211","agreement":true,"isActive":true,"date":1667299576133,"kind":"Connector","isSelected":false,"intensity":3,"isDeletable":true,"isOver":false,"isBidirectional":true,"eventLog":[{"time":1667299576133,"type":"create connection"},{"time":1667299585392,"type":"selected","value":1},{"time":1667299586556,"type":"change intensity of connector","value":3},{"time":1667299586556,"type":"selected","value":0},{"time":1667299588093,"type":"selected","value":1},{"time":1667299589171,"type":"bidirection","value":1},{"time":1667299590140,"type":"change intensity of connector","value":3},{"time":1667299590140,"type":"selected","value":0}]},{"id":"a2b64912-92d0-4e79-8312-cd59e958defa","source":"c6a306cc-13cf-4573-95c0-80db03d2d619","target":"5c4a85a0-9583-4666-b691-376b9e192b79","agreement":true,"isActive":true,"date":1667299649424,"kind":"Connector","isSelected":false,"intensity":3,"isDeletable":true,"isOver":false,"isBidirectional":true,"eventLog":[{"time":1667299649424,"type":"create connection"},{"time":1667299653021,"type":"selected","value":1},{"time":1667299654742,"type":"bidirection","value":1},{"time":1667299657530,"type":"change intensity of connector","value":3},{"time":1667299657530,"type":"selected","value":0}]}],"currentID":{},"currentNode":{},"hasSelectedNode":[false],"currentConnector":{},"hasSelectedConnector":[false],"readyToMove":[false],"isIncoming":[false],"hasElementMoved":[false]}
